INSTALL
LICENSE
README
setup.py
resources/threadpool-1.2.7-patch
resources/testdata/TestShell/sleep.py
resources/testdata/TestShell/dirToStage/0
resources/testdata/TestShell/dirToStage/level1/1
resources/testdata/TestShell/dirToStage/level1/level2/2
src/cloudpool/__init__.py
src/cloudpool/environment.py
src/cloudpool/shell.py
src/cloudpool/task.py
src/cloudpool/utils.py
src/cloudpool.egg-info/PKG-INFO
src/cloudpool.egg-info/SOURCES.txt
src/cloudpool.egg-info/dependency_links.txt
src/cloudpool.egg-info/requires.txt
src/cloudpool.egg-info/top_level.txt
test/TestExecute.py
test/TestKill.py
test/TestShell.py
test/__init__.py
test/config