Metadata-Version: 1.0
Name: cloudpool
Version: 0.1.3
Summary: pool of execution hosts
Home-page: http://code.google.com/p/cloudpool/
Author: michael j pan
Author-email: mikepan@gmail.com
License: New BSD
Keywords: cloud pool execute
Platform: All
